MatplotLibAPI/Area.py
MatplotLibAPI/Bar.py
MatplotLibAPI/BoxViolin.py
MatplotLibAPI/Bubble.py
MatplotLibAPI/Composite.py
MatplotLibAPI/Heatmap.py
MatplotLibAPI/Histogram.py
MatplotLibAPI/Network.py
MatplotLibAPI/Pie.py
MatplotLibAPI/Pivot.py
MatplotLibAPI/Sankey.py
MatplotLibAPI/StyleTemplate.py
MatplotLibAPI/Sunburst.py
MatplotLibAPI/Table.py
MatplotLibAPI/Timeserie.py
MatplotLibAPI/Treemap.py
MatplotLibAPI/Waffle.py
MatplotLibAPI/Wordcloud.py
MatplotLibAPI/__init__.py
MatplotLibAPI/_typing.py
MatplotLibAPI/_visualization_utils.py
MatplotLibAPI/accessor.py
matplotlibapi-3.3.0.dist-info/METADATA
matplotlibapi-3.3.0.dist-info/WHEEL
matplotlibapi-3.3.0.dist-info/licenses/LICENSE
matplotlibapi-3.3.0.dist-info/RECORD
