Metadata-Version: 2.4
Name: MatplotLibAPI
Version: 3.3.0
License-File: LICENSE
Requires-Python: >=3.8
Requires-Dist: kaleido
Requires-Dist: matplotlib
Requires-Dist: nbformat
Requires-Dist: networkx
Requires-Dist: numpy
Requires-Dist: pandas
Requires-Dist: plotly
Requires-Dist: scikit-learn
Requires-Dist: seaborn
Requires-Dist: wordcloud
Provides-Extra: dev
Requires-Dist: black; extra == 'dev'
Requires-Dist: pydocstyle; extra == 'dev'
Requires-Dist: pyright; extra == 'dev'
Requires-Dist: pytest; extra == 'dev'
Requires-Dist: pytest-cov; extra == 'dev'
Requires-Dist: pytest-pydocstyle; extra == 'dev'
Requires-Dist: tomli; extra == 'dev'
